pyteap/__init__.py
pyteap/baseline.py
pyteap/signals/__init__.py
pyteap/signals/bvp.py
pyteap/signals/ecg.py
pyteap/signals/gsr.py
pyteap/signals/hst.py
pyteap/utils/__init__.py
pyteap/utils/exceptions.py
pyteap/utils/filters.py
pyteap/utils/logging.py
PyTEAP-0.1.2.dist-info/LICENSE
PyTEAP-0.1.2.dist-info/METADATA
PyTEAP-0.1.2.dist-info/WHEEL
PyTEAP-0.1.2.dist-info/top_level.txt
PyTEAP-0.1.2.dist-info/RECORD
