Metadata-Version: 2.1
Name: PyTEAP
Version: 0.1.2
Summary: PyTEAP: A Python implementation of Toolbox for Emotion Analysis using Physiological signals (TEAP).
Home-page: https://github.com/cheulyop/PyTEAP
Author: Cheul Young Park
Author-email: cheulyop@gmail.com
License: UNKNOWN
Platform: UNKNOWN
Classifier: Development Status :: 3 - Alpha
Classifier: Programming Language :: Python :: 3
Classifier: License :: OSI Approved :: GNU General Public License v3 (GPLv3)
Classifier: Operating System :: OS Independent
Requires-Python: >=3.6
